ddss/__init__.py
ddss/ds.py
ddss/ds.ts
ddss/dump.py
ddss/dump.ts
ddss/egg.py
ddss/egg.ts
ddss/egraph.py
ddss/egraph.ts
ddss/input.py
ddss/input.ts
ddss/load.py
ddss/load.ts
ddss/main.py
ddss/main.ts
ddss/orm.py
ddss/orm.ts
ddss/output.py
ddss/output.ts
ddss/utility.py
ddss/utility.ts
ddss-0.0.37.dist-info/licenses/LICENSE.md
ddss-0.0.37.dist-info/METADATA
ddss-0.0.37.dist-info/WHEEL
ddss-0.0.37.dist-info/entry_points.txt
ddss-0.0.37.dist-info/top_level.txt
ddss-0.0.37.dist-info/RECORD
