Metadata-Version: 2.4
Name: ddss
Version: 0.0.37
Summary: Distributed Deductive System Sorts
Author-email: Hao Zhang <hzhangxyz@outlook.com>
License-Expression: AGPL-3.0-or-later
Project-URL: Repository, https://github.com/USTC-KnowledgeComputingLab/ddss.git
Requires-Python: >=3.11
License-File: LICENSE.md
Requires-Dist: apyds~=0.0.14
Requires-Dist: apyds-bnf~=0.0.14
Requires-Dist: apyds-egg~=0.0.14
Requires-Dist: prompt-toolkit~=3.0.52
Requires-Dist: sqlalchemy[aiomysql,aiosqlite,postgresql-asyncpg]~=2.0.45
Requires-Dist: tyro~=1.0.3
Provides-Extra: dev
Requires-Dist: pytest~=9.0.2; extra == "dev"
Requires-Dist: pytest-asyncio~=1.3.0; extra == "dev"
Requires-Dist: pytest-cov~=7.0.0; extra == "dev"
Requires-Dist: ruff~=0.14.10; extra == "dev"
Dynamic: license-file
